{
  "name": "Python Poetry Development",
  "image": "mcr.microsoft.com/devcontainers/python:3.11-bullseye",
  "features": {
    "ghcr.io/devcontainers/features/git:1": {},
    "ghcr.io/devcontainers/features/ssh:1": {}
  },
  "customizations": {
    "vscode": {
      "extensions": [
        "ms-python.python",
        "ms-python.black-formatter",
        "ms-python.isort",
        "ms-python.flake8",
        "ms-python.mypy-type-checker",
        "charliermarsh.ruff"
      ],
      "settings": {
        "python.defaultInterpreterPath": "/usr/local/bin/python",
        "python.formatting.provider": "black",
        "python.linting.enabled": true,
        "python.linting.flake8Enabled": true,
        "python.linting.mypyEnabled": true,
        "[python]": {
          "editor.formatOnSave": true,
          "editor.codeActionsOnSave": {
            "source.organizeImports": true
          }
        }
      }
    }
  },
  "postCreateCommand": [
    "bash",
    "-c",
    "curl -LsSf https://astral.sh/uv/install.sh | sh && echo 'export PATH=\"$HOME/.cargo/bin:$PATH\"' >> ~/.bashrc"
  ],
  "remoteUser": "vscode"
}